hatebpy/__init__.py
hatebpy/_api.py
hatebpy/_auth.py
hatebpy/_cli.py
hatebpy/_feed.py
hatebpy/model.py
hatebpy-0.1.0.dist-info/LICENSE
hatebpy-0.1.0.dist-info/METADATA
hatebpy-0.1.0.dist-info/WHEEL
hatebpy-0.1.0.dist-info/entry_points.txt
hatebpy-0.1.0.dist-info/top_level.txt
hatebpy-0.1.0.dist-info/RECORD
