Metadata-Version: 2.1
Name: hatebpy
Version: 0.1.0
Summary: A Python package for easy interaction with the Hatena Bookmark API
Author-email: K <kmyashi@rmc-8.com>
License: MIT License
Project-URL: Homepage, https://github.com/rmc8/hatebpy
Requires-Python: >=3.8
License-File: LICENSE
Requires-Dist: requests >=2.32.3
Requires-Dist: requests-oauthlib >=2.0.0
Requires-Dist: fire >=0.5.0
Requires-Dist: feedparser >=6.0.11
Requires-Dist: pydantic >=2.0.0
